{
    "WR-P-E-A": "Discussion lists",
    "WR-P-E-C": "E-magazines",
    "WR-P-E-E": "Newsletters",
    "WR-P-E-F": "Press releases",
    "WR-P-E-G": "Subtitles",
    "WR-P-E-H": "Teletext pages",
    "WR-P-E-I": "Websites",
    "WR-P-E-J": "Wikipedia",
    "WR-P-E-K": "Blogs",
    "WR-P-E-L": "Tweets",
    "WR-P-P-B": "Books",
    "WR-P-P-C": "Brochures",
    "WR-P-P-D": "Newsletters",
    "WR-P-P-E": "Guides & manuals",
    "WR-P-P-F": "Legal texts",
    "WR-P-P-G": "Newspapers",
    "WR-P-P-H": "Periodicals & magazines",
    "WR-P-P-I": "Policy documents",
    "WR-P-P-J": "Proceedings",
    "WR-P-P-K": "Reports",
    "WR-U-E-A": "Chats",
    "WR-U-E-D": "SMS",
    "WR-U-E-E": "Written assignments",
    "WS-U-E-A": "Auto cues",
    "WS-U-T-B": "Texts for the visually impaired"
}